bream4/__init__.py
bream4/cli/__init__.py
bream4/cli/hasher.py
bream4/device_interfaces/__init__.py
bream4/device_interfaces/device_wrapper.py
bream4/device_interfaces/devices/__init__.py
bream4/device_interfaces/devices/base_device.py
bream4/device_interfaces/devices/minion.py
bream4/device_interfaces/devices/promethion.py
bream4/legacy/__init__.py
bream4/legacy/device_interfaces/__init__.py
bream4/legacy/device_interfaces/devices/__init__.py
bream4/legacy/device_interfaces/devices/base_device.py
bream4/legacy/device_interfaces/devices/minion.py
bream4/legacy/device_interfaces/devices/promethion.py
bream4/legacy/toolkit/__init__.py
bream4/legacy/toolkit/analysis/__init__.py
bream4/legacy/toolkit/analysis/metrics/__init__.py
bream4/legacy/toolkit/analysis/metrics/utils/__init__.py
bream4/legacy/toolkit/analysis/metrics/utils/signal.py
bream4/pb/__init__.py
bream4/pb/protocol_ui_pb2.py
bream4/pb/bream/__init__.py
bream4/pb/bream/experiment_estimated_end_pb2.py
bream4/pb/bream/hardware_check_result_pb2.py
bream4/pb/bream/mux_scan_results_pb2.py
bream4/pb/bream/platform_qc_results_pb2.py
bream4/pb/bream/protocol_communication_pb2.py
bream4/toolkit/__init__.py
bream4/toolkit/analysis/__init__.py
bream4/toolkit/analysis/assessment/__init__.py
bream4/toolkit/analysis/assessment/pixel_blocks.py
bream4/toolkit/analysis/metrics/__init__.py
bream4/toolkit/analysis/metrics/waveform_utilities.py
bream4/toolkit/calibration/__init__.py
bream4/toolkit/calibration/calibrate_device.py
bream4/toolkit/calibration/calibrate_voltage_offset.py
bream4/toolkit/calibration/minion_like.py
bream4/toolkit/calibration/promethion.py
bream4/toolkit/pings/__init__.py
bream4/toolkit/pings/ping_dumping.py
bream4/toolkit/pings/ping_generation.py
bream4/toolkit/procedure_components/__init__.py
bream4/toolkit/procedure_components/data_types.py
bream4/toolkit/procedure_components/dict_utils.py
bream4/toolkit/procedure_components/feature_manager.py
bream4/toolkit/procedure_components/grpc_streamer.py
nanodeep-0.0.3.dist-info/LICENSE
nanodeep-0.0.3.dist-info/METADATA
nanodeep-0.0.3.dist-info/WHEEL
nanodeep-0.0.3.dist-info/entry_points.txt
nanodeep-0.0.3.dist-info/top_level.txt
nanodeep-0.0.3.dist-info/RECORD
