Metadata-Version: 2.1
Name: nanodeep
Version: 0.0.3
Summary: A package used to achieve adaptive sample
Home-page: https://github.com/shadow-lang
Author: Yusen Lin
Author-email: 1014903773@qq.com
License: MIT License
Classifier: Programming Language :: Python :: 3
Classifier: License :: OSI Approved :: MIT License
Classifier: Operating System :: OS Independent
Requires-Python: >=3.7
License-File: LICENSE
Requires-Dist: numpy (>=1.20.0)
Requires-Dist: torch (>=1.13.1)
Requires-Dist: torchmetrics (==0.9.0)
Requires-Dist: matplotlib (>=3.4.0)
Requires-Dist: ont-fast5-api (>=4.1.1)
Requires-Dist: scikit-learn (>=1.0)
Requires-Dist: tqdm (>=4.64.1)
Requires-Dist: PyYAML (>=6.0)
Requires-Dist: importlib-metadata (>=6.0.0)
Requires-Dist: importlib-resources (>=5.12.0)
Requires-Dist: grpcio (>=1.47.0)
Requires-Dist: protobuf (>=3.20.1)
